nemo_agent/__init__.py
nemo_agent/main.py
nemo_agent-5.0.3.dist-info/LICENSE
nemo_agent-5.0.3.dist-info/METADATA
nemo_agent-5.0.3.dist-info/WHEEL
nemo_agent-5.0.3.dist-info/entry_points.txt
nemo_agent-5.0.3.dist-info/RECORD
