Metadata-Version: 2.3
Name: nemo-agent
Version: 5.0.3
Summary: Your Python AI Coder
License: MIT
Keywords: ai,agent,ai agent,local ai agent,python ai agent
Author: Bevan Hunt
Author-email: bevan@bevanhunt.com
Requires-Python: >=3.10,<4.0
Classifier: License :: OSI Approved :: MIT License
Classifier: Operating System :: OS Independent
Classifier: Programming Language :: Python :: 3
Classifier: Programming Language :: Python :: 3.10
Classifier: Programming Language :: Python :: 3.11
Classifier: Programming Language :: Python :: 3.12
Classifier: Programming Language :: Python :: 3.13
Classifier: Programming Language :: Python :: 3 :: Only
Classifier: Topic :: Scientific/Engineering :: Artificial Intelligence
Requires-Dist: click
Requires-Dist: openai
Requires-Dist: tiktoken (==0.9.0)
Project-URL: Homepage, https://nemo-agent.com
Project-URL: Repository, https://github.com/truemagic-coder/nemo-agent
